canvas_ux/__init__.py
canvas_ux/_default_codes.py
canvas_ux/_frontend.py
canvas_ux/_helpers.py
canvas_ux/_jupyter_utils.py
canvas_ux/_specs.py
canvas_ux/_version.py
canvas_ux/_widgets.py
canvas_ux/canvas.py
canvas_ux/labextension/package.json
canvas_ux/labextension/static/509.325fa3659d2c75120c40.js
canvas_ux/labextension/static/remoteEntry.c5954d06a28b2336f554.js
canvas_ux/labextension/static/style.js
canvas_ux/labextension/static/third-party-licenses.json
canvas_ux/nbextension/extension.js
canvas_ux/nbextension/index.js
canvas_ux/standalone/favicon.png
canvas_ux/standalone/index.html
canvas_ux/standalone/widgets/StandaloneApp.js
canvas_ux/standalone/widgets/StandaloneApp.js.map
canvas_ux-3.9.6.data/data/etc/jupyter/nbconfig/notebook.d/canvas_ux.json
canvas_ux-3.9.6.data/data/share/jupyter/labextensions/canvas-ux/install.json
canvas_ux-3.9.6.data/data/share/jupyter/labextensions/canvas-ux/package.json
canvas_ux-3.9.6.data/data/share/jupyter/labextensions/canvas-ux/static/509.325fa3659d2c75120c40.js
canvas_ux-3.9.6.data/data/share/jupyter/labextensions/canvas-ux/static/remoteEntry.c5954d06a28b2336f554.js
canvas_ux-3.9.6.data/data/share/jupyter/labextensions/canvas-ux/static/style.js
canvas_ux-3.9.6.data/data/share/jupyter/labextensions/canvas-ux/static/third-party-licenses.json
canvas_ux-3.9.6.data/data/share/jupyter/nbextensions/canvas_ux/extension.js
canvas_ux-3.9.6.data/data/share/jupyter/nbextensions/canvas_ux/index.js
canvas_ux-3.9.6.dist-info/METADATA
canvas_ux-3.9.6.dist-info/WHEEL
canvas_ux-3.9.6.dist-info/top_level.txt
canvas_ux-3.9.6.dist-info/RECORD
